optioneer/__init__.py
optioneer/lib.py
optioneer-1.0.3.dist-info/METADATA
optioneer-1.0.3.dist-info/RECORD
optioneer-1.0.3.dist-info/WHEEL
optioneer-1.0.3.dist-info/top_level.txt
optioneer-1.0.3.dist-info/zip-safe
