Metadata-Version: 2.1
Name: optioneer
Version: 1.0.3
Summary: Nestable, tab-able options for use in Python programs
Home-page: https://github.com/topper-123/optioneer
Author: Terji Petersen
Author-email: contribute@tensortable.com
License: BSD license
Keywords: optioneer
Platform: UNKNOWN
Classifier: Development Status :: 5 - Production/Stable
Classifier: Intended Audience :: Developers
Classifier: License :: OSI Approved :: BSD License
Classifier: Natural Language :: English
Classifier: Programming Language :: Python :: 2
Classifier: Programming Language :: Python :: 2.7
Classifier: Programming Language :: Python :: 3
Classifier: Programming Language :: Python :: 3.4
Classifier: Programming Language :: Python :: 3.5
Classifier: Programming Language :: Python :: 3.6
Classifier: Programming Language :: Python :: 3.7
